{"JID":"NHEM,110,湖簡,263,20210728,1","JYEAR":"110","JCASE":"湖簡","JNO":"263","JDATE":"20210728","JTITLE":"違反毒品危害防制條例","JFULL":"臺灣士林地方法院刑事簡易判決　　　　110年度湖簡字第263號\r\n聲　請　人　臺灣士林地方檢察署檢察官\r\n被　　　告　鄭執我\r\n\r\n\r\n上列被告因違反毒品危害防制條例案件，經檢察官江耀民聲請以\r\n簡易判決處刑（110年度偵字第10312號），本院判決如下：\r\n    主  文\r\n鄭執我持有第二級毒品，累犯，處拘役參拾日，如易科罰金，以\r\n新臺幣壹仟元折算壹日。\r\n扣案之第二級毒品大麻壹包（含包裝袋，驗餘淨重零點玖柒柒伍\r\n公克）沒收銷燬之。\r\n    事實及理由\r\n一、本件犯罪事實、證據及應適用之法條，均引用檢察官聲請簡\r\n    易判決處刑書之記載（如附件）。本件被告之前案事實部分\r\n    ，應補充：「被告前因妨害風化案件，經臺灣新北地方院以\r\n    108年度審訴字第136號判決處有期徒刑5月確定，並於民國\r\n    108年7月22日易科罰金執行完畢（於本案構成累犯）」；應\r\n    適用之法條並應補充如下：刑事訴訟法第449條第1項前段、\r\n    第3項、第450條第1項、第454條第2項，刑法第11條、第41\r\n    條第1項前段、第47條第1項。又本件被告為累犯，經依釋字\r\n    第775號解釋意旨裁量結果，不加重其最低本刑，併此敘明\r\n    。\r\n二、關於沒收部分，扣案之第二級毒品大麻1包（含包裝袋，驗\r\n    餘淨重0.9775公克），經查驗確為第二級毒品大麻（109年\r\n    度毒偵字第1735號卷第131頁），依毒品危害防制條例第18\r\n    條第1項前段規定，宣告沒收銷燬之。\r\n三、如不服本判決，應於判決送達後20日內，向本院提出上訴狀\r\n    （應附繕本），上訴於本院合議庭。\r\n中    華    民    國   110    年    7     月    28    日\r\n                  內湖簡易庭法  官  鄭欣怡\r\n以上正本證明與原本無異。\r\n如不服本判決，應於判決送達後20日內，向本院提出上訴狀（應\r\n附繕本），上訴於本院合議庭。\r\n中    華    民    國   110    年    7     月    28    日\r\n                            書記官  王盈淳\r\n附錄本案論罪科刑法條全文：\r\n毒品危害防制條例第11條\r\n持有第一級毒品者，處3年以下有期徒刑、拘役或新臺幣5萬元以\r\n下罰金。\r\n持有第二級毒品者，處2年以下有期徒刑、拘役或新臺幣3萬元以\r\n下罰金。\r\n持有第一級毒品純質淨重十公克以上者，處1年以上7年以下有期\r\n徒刑，得併科新臺幣1百萬元以下罰金。\r\n持有第二級毒品純質淨重二十公克以上者，處6月以上5年以下有\r\n期徒刑，得併科新臺幣70萬元以下罰金。\r\n持有第三級毒品純質淨重二十公克以上者，處3年以下有期徒刑\r\n，得併科新臺幣30萬元以下罰金。\r\n持有第四級毒品純質淨重二十公克以上者，處1年以下有期徒刑\r\n，得併科新臺幣10萬元以下罰金。\r\n持有專供製造或施用第一級、第二級毒品之器具者，處1年以下\r\n有期徒刑、拘役或新臺幣1萬元以下罰金。"}